flask_api_autodoc/__init__.py
flask_api_autodoc/docstring.py
flask_api_autodoc/template.html
flask_api_autodoc/view.py
flask_api_autodoc-1.0.0.dist-info/WHEEL
flask_api_autodoc-1.0.0.dist-info/METADATA
flask_api_autodoc-1.0.0.dist-info/RECORD
