Metadata-Version: 2.1
Name: flask-api-autodoc
Version: 1.0.0
Summary: A Python module to generate a page documenting the API of a Flask application.
Home-page: https://github.com/lsiden/flask-api-autodoc
License: MIT
Author: Lawrence Siden
Author-email: lsiden@gmail.com
Requires-Python: >=3.8,<4.0
Classifier: Framework :: Flask
Classifier: License :: OSI Approved :: MIT License
Classifier: Programming Language :: Python :: 3
Classifier: Programming Language :: Python :: 3.8
Classifier: Programming Language :: Python :: 3.9
Classifier: Topic :: Software Development :: Documentation
Requires-Dist: Flask (>=1.1.2,<2.0.0)
